daiquiri/__init__.py
daiquiri/__main__.py
daiquiri/auth/__init__.py
daiquiri/auth/adapter.py
daiquiri/auth/admin.py
daiquiri/auth/apps.py
daiquiri/auth/forms.py
daiquiri/auth/handlers.py
daiquiri/auth/models.py
daiquiri/auth/permissions.py
daiquiri/auth/serializers.py
daiquiri/auth/settings.py
daiquiri/auth/signals.py
daiquiri/auth/urls_accounts.py
daiquiri/auth/urls_auth.py
daiquiri/auth/utils.py
daiquiri/auth/validators.py
daiquiri/auth/views.py
daiquiri/auth/viewsets.py
daiquiri/auth/assets/js/users.js
daiquiri/auth/assets/js/api/AuthApi.js
daiquiri/auth/assets/js/components/ConfirmModal.js
daiquiri/auth/assets/js/components/ShowModal.js
daiquiri/auth/assets/js/components/UpdateModal.js
daiquiri/auth/assets/js/components/Users.js
daiquiri/auth/assets/js/hooks/mutations.js
daiquiri/auth/assets/js/hooks/queries.js
daiquiri/auth/migrations/0001_profile_model.py
daiquiri/auth/migrations/0002_profile_attributes.py
daiquiri/auth/migrations/0003_view_permission.py
daiquiri/auth/migrations/0004_view_permission_typo.py
daiquiri/auth/migrations/0005_view_permission_fix.py
daiquiri/auth/migrations/0006_profile_ordering.py
daiquiri/auth/migrations/0007_profile_is_confirmed.py
daiquiri/auth/migrations/0008_profile_is_pending.py
daiquiri/auth/migrations/0009_delete_detailkey.py
daiquiri/auth/migrations/0010_profile_consent.py
daiquiri/auth/migrations/0011_meta.py
daiquiri/auth/migrations/0012_django2.py
daiquiri/auth/migrations/0013_alter_profile_id.py
daiquiri/auth/migrations/0014_use_django_jsonfield.py
daiquiri/auth/migrations/__init__.py
daiquiri/auth/static/auth/js/users.js
daiquiri/auth/static/auth/js/users.js.LICENSE.txt
daiquiri/auth/templates/account/account_inactive.html
daiquiri/auth/templates/account/account_pending.html
daiquiri/auth/templates/account/account_profile.html
daiquiri/auth/templates/account/account_token.html
daiquiri/auth/templates/account/email.html
daiquiri/auth/templates/account/email_confirm.html
daiquiri/auth/templates/account/login.html
django_daiquiri-1.3.2.dist-info/licenses/AUTHORS
django_daiquiri-1.3.2.dist-info/licenses/LICENSE
django_daiquiri-1.3.2.dist-info/licenses/NOTICE
django_daiquiri-1.3.2.dist-info/METADATA
django_daiquiri-1.3.2.dist-info/WHEEL
django_daiquiri-1.3.2.dist-info/entry_points.txt
django_daiquiri-1.3.2.dist-info/top_level.txt
django_daiquiri-1.3.2.dist-info/RECORD
