Metadata-Version: 2.4
Name: django-daiquiri
Version: 1.3.2
Summary: Daiquiri is a framework for the publication of scientific databases.
Author-email: Jochen Klar <mail@jochenklar.de>, Anastasia Galkin <agalkin@aip.de>, Yori Fournier <y.fournier@aip.de>, Kirill Makan <kmakan@aip.de>, Simeon Reusch <sreusch@aip.de>
License: Apache-2.0
Project-URL: documentation, https://django-daiquiri.github.io
Project-URL: homepage, https://django-daiquiri.github.io
Project-URL: issues, https://github.com/django-daiquiri/daiquiri/issues
Project-URL: repository, https://github.com/django-daiquiri/daiquiri.git
Classifier: Development Status :: 5 - Production/Stable
Classifier: Environment :: Web Environment
Classifier: Framework :: Django :: 5.2
Classifier: Intended Audience :: Science/Research
Classifier: License :: OSI Approved :: Apache Software License
Classifier: Operating System :: OS Independent
Classifier: Programming Language :: Python
Classifier: Programming Language :: Python :: 3 :: Only
Classifier: Programming Language :: Python :: 3.13
Requires-Python: >=3.13
License-File: LICENSE
License-File: NOTICE
License-File: AUTHORS
Requires-Dist: astropy<7.3,>=7.1
Requires-Dist: celery<5.7.0,>=5.5.3
Requires-Dist: Django~=5.2.5
Requires-Dist: django-allauth[openid,socialaccount]<65.14,>=65.11
Requires-Dist: python-dotenv<1.3.0,>=1.1.1
Requires-Dist: django-extensions~=4.1
Requires-Dist: django-filter~=25.1
Requires-Dist: django-honeypot~=1.3.0
Requires-Dist: django-ipware~=7.0.1
Requires-Dist: django-sendfile2~=0.7.2
Requires-Dist: django-settings-export~=1.2.1
Requires-Dist: django-user-agents~=0.4.0
Requires-Dist: django-widget-tweaks~=1.5.0
Requires-Dist: djangorestframework~=3.16.1
Requires-Dist: dj-database-url~=3.0.1
Requires-Dist: drf-extensions~=0.8.0
Requires-Dist: ipaddress~=1.0.23
Requires-Dist: iso8601~=2.1.0
Requires-Dist: jsonfield~=3.2.0
Requires-Dist: lunr~=0.8.0
Requires-Dist: Markdown<3.11.0,>=3.8.2
Requires-Dist: pandas~=2.3.2
Requires-Dist: passlib>=1.7.4
Requires-Dist: pyarrow>=21.0.0
Requires-Dist: Pygments~=2.19.2
Requires-Dist: PyJWT~=2.10.1
Requires-Dist: queryparser-python3~=0.7.4
Requires-Dist: rules~=3.5
Requires-Dist: sqlalchemy~=2.0.43
Requires-Dist: XlsxWriter==3.2.9
Provides-Extra: ci
Requires-Dist: coveralls; extra == "ci"
Requires-Dist: django-daiquiri[postgres]; extra == "ci"
Requires-Dist: django-daiquiri[pytest]; extra == "ci"
Provides-Extra: dev
Requires-Dist: build; extra == "dev"
Requires-Dist: pre-commit; extra == "dev"
Requires-Dist: ruff; extra == "dev"
Requires-Dist: twine; extra == "dev"
Requires-Dist: django-daiquiri[pytest]; extra == "dev"
Provides-Extra: gunicorn
Requires-Dist: gunicorn>=23.0; extra == "gunicorn"
Provides-Extra: postgres
Requires-Dist: psycopg[binary]<3.4.0,>=3.2.9; extra == "postgres"
Provides-Extra: pytest
Requires-Dist: coverage<7.14.0,>=7.10.5; extra == "pytest"
Requires-Dist: pytest<9.1.0,>=8.4.1; extra == "pytest"
Requires-Dist: pytest-cov~=6.2.0; extra == "pytest"
Requires-Dist: pytest-django~=4.11.1; extra == "pytest"
Requires-Dist: pytest-dotenv~=0.5.2; extra == "pytest"
Requires-Dist: pytest-mock<3.16.0,>=3.14.1; extra == "pytest"
Dynamic: license-file
